<?xml version="1.0" encoding="UTF-8"?>
<datasources xmlns="http://www.jboss.org/ironjacamar/schema"
    xmlns:xsi="http://www.w3.org/2001/XMLSchema-instance"
    xsi:schemaLocation="http://www.jboss.org/ironjacamar/schema http://docs.jboss.org/ironjacamar/schema/datasources_1_0.xsd">
  <datasource jndi-name="java:/CBTDS" pool-name="CBTPool">
      <connection-url>
          jdbc:mysql://mysql:3306/cbt
      </connection-url>
      <driver>
         mysql
      </driver>
      <pool>
          <max-pool-size>
              30
          </max-pool-size>
      </pool>
      <security>
          <user-name>
              admin
          </user-name>
          <password>
              password
          </password>
      </security>
  </datasource>
  <drivers>
     <driver name="mysql" module="com.mysql"/>
  </drivers>
</datasources>
 
